jdti/__init__.py
jdti/jdti.py
jdti/utils.py
jdti-0.2.2.dist-info/licenses/license.txt
jdti-0.2.2.dist-info/METADATA
jdti-0.2.2.dist-info/WHEEL
jdti-0.2.2.dist-info/RECORD
