Metadata-Version: 2.4
Name: jdti
Version: 0.2.2
Summary: 
License-File: license.txt
Author: jkubis96
Author-email: jbiosystem@gmail.com
Requires-Python: >=3.12,<3.13
Classifier: Programming Language :: Python :: 3
Classifier: Programming Language :: Python :: 3.12
Requires-Dist: adjusttext (>=1.3.0,<2.0.0)
Requires-Dist: harmonypy (==0.0.10)
Requires-Dist: joblib (>=1.5.2,<2.0.0)
Requires-Dist: matplotlib (>=3.10.6,<4.0.0)
Requires-Dist: numpy (>=2.3.3,<3.0.0)
Requires-Dist: pandas (>=2.3.2,<3.0.0)
Requires-Dist: plotly (>=6.3.0,<7.0.0)
Requires-Dist: scikit-learn (>=1.7.2,<2.0.0)
Requires-Dist: scipy (>=1.16.2,<2.0.0)
Requires-Dist: seaborn (>=0.13.2,<0.14.0)
Requires-Dist: tqdm (>=4.67.1,<5.0.0)
Requires-Dist: umap-learn (>=0.5.9.post2,<0.6.0)
